sqliteTool/__init__.py
sqliteTool/sqlite_tool.py
testTool/__init__.py
testTool/test1.py
sss_tools-0.0.2.dist-info/METADATA
sss_tools-0.0.2.dist-info/WHEEL
sss_tools-0.0.2.dist-info/top_level.txt
sss_tools-0.0.2.dist-info/RECORD
