Metadata-Version: 2.1
Name: sss-tools
Version: 0.0.2
Summary: A simple sqlite package
Author: sss758
Author-email: author@example.com
Classifier: Programming Language :: Python :: 3
Classifier: License :: OSI Approved :: MIT License
Classifier: Operating System :: OS Independent
Requires-Python: >=3.8
Requires-Dist: requests
